trzsz_libs-1.1.4-py3.11-nspkg.pth
tests/__init__.py
tests/test_transfer_action.py
tests/test_transfer_config.py
tests/test_utils_function.py
tests/trzsz/__init__.py
tests/trzsz/libs/__init__.py
tests/trzsz/libs/__version__.py
tests/trzsz/libs/transfer.py
tests/trzsz/libs/utils.py
tests/trzsz/libs/wins.py
trzsz/libs/__init__.py
trzsz/libs/__version__.py
trzsz/libs/transfer.py
trzsz/libs/utils.py
trzsz/libs/wins.py
trzsz_libs-1.1.4.dist-info/METADATA
trzsz_libs-1.1.4.dist-info/WHEEL
trzsz_libs-1.1.4.dist-info/namespace_packages.txt
trzsz_libs-1.1.4.dist-info/top_level.txt
trzsz_libs-1.1.4.dist-info/RECORD
