Metadata-Version: 2.1
Name: trzsz-libs
Version: 1.1.4
Summary: trzsz is a simple file transfer tools, similar to lrzsz ( rz / sz ) and compatible with tmux, which works with iTerm2 and has a nice progress bar.
Home-page: https://trzsz.github.io
Author: Lonny Wong
Author-email: lonnywong@qq.com
License: MIT License
Keywords: trzsz trz tsz lrzsz rz sz tmux iTerm2 progressbar
Classifier: Development Status :: 5 - Production/Stable
Classifier: Environment :: Console
Classifier: Intended Audience :: Developers
Classifier: Intended Audience :: Science/Research
Classifier: Intended Audience :: System Administrators
Classifier: License :: OSI Approved :: MIT License
Classifier: Natural Language :: English
Classifier: Operating System :: MacOS
Classifier: Operating System :: POSIX
Classifier: Operating System :: POSIX :: Linux
Classifier: Operating System :: Microsoft :: Windows
Classifier: Programming Language :: Python
Classifier: Programming Language :: Python :: 2
Classifier: Programming Language :: Python :: 3
Classifier: Topic :: Utilities
